sqlizer/__init__.py
sqlizer/connector.py
sqlizer/functions.py
sqlizer/processor.py
sqlizer/sqlizer.py
sqlizer/workflow.schema.json
sqlizer-0.0.1.dist-info/LICENSE
sqlizer-0.0.1.dist-info/METADATA
sqlizer-0.0.1.dist-info/WHEEL
sqlizer-0.0.1.dist-info/entry_points.txt
sqlizer-0.0.1.dist-info/top_level.txt
sqlizer-0.0.1.dist-info/RECORD
