Metadata-Version: 2.1
Name: sqlizer
Version: 0.0.1
Summary: Orchestration service for SQL only ETL workflows.
Home-page: https://github.com/thingsplode/sqlizer
Author: thingsplode
Author-email: tamas.csaba@gmail.com
License: Apache 2.0
Keywords: microservice,ETL,SQL,ETL Workflow,ETL Pipeline,DWH,data warehouse,airflow,luigi,orchestration
Platform: any
Classifier: Environment :: Console
Classifier: Environment :: Web Environment
Classifier: Intended Audience :: Developers
Classifier: Operating System :: POSIX
Classifier: License :: OSI Approved :: Apache Software License
Classifier: Programming Language :: Python :: 3
Requires-Dist: psycopg2
Requires-Dist: pyyaml
Requires-Dist: enum34
Requires-Dist: simplejson
Requires-Dist: boto3
Requires-Dist: tabulate
Requires-Dist: jinja2
